pyEddyTracker-3.6.1.data/scripts/EddyFinalTracking
pyEddyTracker-3.6.1.data/scripts/EddyMergeCorrespondances
pyEddyTracker-3.6.1.data/scripts/EddySubSetter
pyEddyTracker-3.6.1.data/scripts/EddyTranslate
py_eddy_tracker/__init__.py
py_eddy_tracker/_version.py
py_eddy_tracker/eddy_feature.py
py_eddy_tracker/generic.py
py_eddy_tracker/gui.py
py_eddy_tracker/misc.py
py_eddy_tracker/poly.py
py_eddy_tracker/tracking.py
py_eddy_tracker/appli/__init__.py
py_eddy_tracker/appli/eddies.py
py_eddy_tracker/appli/grid.py
py_eddy_tracker/appli/gui.py
py_eddy_tracker/appli/misc.py
py_eddy_tracker/appli/network.py
py_eddy_tracker/data/20160707000000-GOS-L4_GHRSST-SSTfnd-OISST_HR_REP-BLK-v02.0-fv01.0.nc
py_eddy_tracker/data/Anticyclonic_20160515.nc
py_eddy_tracker/data/Anticyclonic_20190223.nc
py_eddy_tracker/data/Cyclonic_20160515.nc
py_eddy_tracker/data/Cyclonic_20190223.nc
py_eddy_tracker/data/__init__.py
py_eddy_tracker/data/dt_blacksea_allsat_phy_l4_20160707_20200801.nc
py_eddy_tracker/data/dt_med_allsat_phy_l4_2005T2.nc
py_eddy_tracker/data/dt_med_allsat_phy_l4_20160515_20190101.nc
py_eddy_tracker/data/loopers_lumpkin_med.nc
py_eddy_tracker/data/mask_1_60.nc
py_eddy_tracker/data/network_med.nc
py_eddy_tracker/data/nrt_global_allsat_phy_l4_20190223_20190226.nc
py_eddy_tracker/dataset/__init__.py
py_eddy_tracker/dataset/grid.py
py_eddy_tracker/featured_tracking/__init__.py
py_eddy_tracker/featured_tracking/area_tracker.py
py_eddy_tracker/featured_tracking/mask_old.nc
py_eddy_tracker/featured_tracking/old_tracker_reference.py
py_eddy_tracker/observations/__init__.py
py_eddy_tracker/observations/groups.py
py_eddy_tracker/observations/network.py
py_eddy_tracker/observations/observation.py
py_eddy_tracker/observations/tracking.py
pyEddyTracker-3.6.1.dist-info/COPYING
pyEddyTracker-3.6.1.dist-info/METADATA
pyEddyTracker-3.6.1.dist-info/WHEEL
pyEddyTracker-3.6.1.dist-info/entry_points.txt
pyEddyTracker-3.6.1.dist-info/top_level.txt
pyEddyTracker-3.6.1.dist-info/RECORD
