Metadata-Version: 2.1
Name: pyEddyTracker
Version: 3.6.1
Summary: Py-Eddy-Tracker libraries
Author: emason & adelepoulle
Author-email: emason@imedea.uib-csic.es
Keywords: eddy science,eddy tracking,eddy tracker
Classifier: Development Status :: 3 - Alpha
Classifier: Topic :: Scientific/Engineering :: Physics
Classifier: Programming Language :: Python
Requires-Python: >=3.7
License-File: COPYING
Requires-Dist: matplotlib
Requires-Dist: opencv-python
Requires-Dist: pint (==0.18)
Requires-Dist: polygon3
Requires-Dist: pyyaml
Requires-Dist: requests
Requires-Dist: scipy
Requires-Dist: zarr
Requires-Dist: netCDF4 (<1.6)
Requires-Dist: numpy (<1.23)
Requires-Dist: numba (<0.56)
